[
    {
        "id": 1,
        "question": "새로운 취미를 시작할 때 당신의 스타일은?",
        "options": [
            {
                "text": "일단 도구나 장비부터 꼼꼼히 알아보고 준비한다",
                "score": {
                    "J": 2
                }
            },
            {
                "text": "일단 흥미가 생기는 대로 가볍게 시작해본다",
                "score": {
                    "P": 2
                }
            }
        ]
    },
    {
        "id": 2,
        "question": "처음 가본 카페에서 메뉴를 고를 때?",
        "options": [
            {
                "text": "실패 없는 베스트 메뉴나 늘 먹던 것을 시킨다",
                "score": {
                    "S": 2
                }
            },
            {
                "text": "그날의 기분에 따라 새롭고 독특한 메뉴를 시도한다",
                "score": {
                    "N": 2
                }
            }
        ]
    },
    {
        "id": 3,
        "question": "친구의 고민 상담을 해줄 때 나의 스타일은?",
        "options": [
            {
                "text": "구체적인 원인을 분석하고 현실적인 조언을 건넨다",
                "score": {
                    "T": 1,
                    "S": 1
                }
            },
            {
                "text": "친구의 마음이 상하지 않게 다독이며 감정에 공감한다",
                "score": {
                    "F": 1,
                    "N": 1
                }
            }
        ]
    }
]